{
  "id": "doc_15_47",
  "title": "Ministério da Saúde e Ipea debatem Índice de Vulnerabilidade Social e Ambiental para o SUS",
  "content": "Estratégia levará em conta fatores ambientais, além de diferentes necessidades intramunicipais, para orientar decisões e financiar a atenção primária\n![Foto: Divulgação/MS](https://www.gov.br/saude/pt-br/assuntos/noticias/2026/marco/ministerio-da-saude-e-ipea-debatem-indice-de-vulnerabilidade-social-e-ambiental-para-o-sus/foto-divulgacao-ms.jpg/@@images/c6ce315d-aeda-415d-8604-e1bfcefe0706.jpeg)\n\nAtualmente, o Índice de Vulnerabilidade Social (IVS) já é utilizado no SUS. O cofinanciamento federal da atenção primária, por exemplo, leva em conta esse indicador de desigualdades, ou seja, a classificação de vulnerabilidade social do município impacta nos recursos que ele recebe. “Entendemos que é fundamental agregar a dimensão ambiental. A gente precisa repensar o impacto que as mudanças climáticas têm no fazer saúde para que a cobertura não fique prejudicada e que possamos atuar com mais assertividade”, pontuou o secretário adjunto de [Atenção Primária à Saúde](https://www.gov.br/saude/pt-br/composicao/saps), Ilano Barreto, que lembrou de outras iniciativas da pasta, como o [AdaptaSUS](https://www.gov.br/saude/pt-br/centrais-de-conteudo/apresentacoes/2025/adaptasus.pdf).\n\nO diretor de programa da [Secretaria Executiva](https://www.gov.br/saude/pt-br/se), Nilton Pereira Junior, reforçou a intersetorialidade do SUS e lembrou que, além dos desastres extremos cada vez mais frequentes, como enchentes, as doenças também são determinadas ambientalmente. “Doenças infectocontagiosas, como a dengue, por exemplo, que é uma arbovirose, estão relacionadas ao desmatamento”, afirmou.\n\n**Diferenças dentro do município**\n\nOutro ponto central do seminário foi a expansão das Unidades de Desenvolvimento Humano (UDH), que permitem uma leitura intramunicipal dos dados censitários. Com essa metodologia, será possível identificar desigualdades dentro das próprias cidades, superando a limitação de análises feitas apenas no nível municipal.\n\n“Sair da visão municipal para a visão intramunicipal, na medida do possível, é uma demanda antiga. E isso é fundamental, porque a gente sabe que o Brasil é muito diverso e os contextos locais são muito diferentes”, acrescentou a presidente do Ipea, Luciana Servo, que lembrou da capilaridade territorial da atenção primária, essencial para esse trabalho.\n\nA iniciativa permitirá ampliar significativamente a cobertura territorial dessa análise, alcançando todos os municípios com mais de 100 mil habitantes e as regiões metropolitanas do País, o que representa mais de 60% da população brasileira. “Para a saúde pública, esse avanço é estratégico, pois amplia nossa capacidade de compreender as vulnerabilidades com maior precisão territorial e de orientar decisões mais qualificadas sobre a localização da necessidade de oferta de serviços e a organização das redes de atenção intersetoriais”, concluiu o coordenador-geral de Financiamento da Atenção Primária, Dirceu Klitzke.\n\nO seminário ainda promoveu oficinas com instituições de pesquisa, planejamento e produção de dados e iniciou a formação de uma rede nacional de pesquisadores para apoiar o desenvolvimento metodológico e o acompanhamento das análises ao longo da cooperação técnica entre o Ministério da Saúde e o Ipea.\n\nO evento, realizado em parceria com a Agência Nacional do Sistema Único de Saúde (AgSUS), também contou com representantes da Casa Civil, dos ministérios do Planejamento e Orçamento, do Desenvolvimento e Assistência Social e do Meio Ambiente, além do Conselho Nacional de Secretários de Saúde (Conass).\n\n*Laísa Queiroz*  \n*Ministério da Saúde*",
  "category": "Meio Ambiente",
  "length": 3572,
  "metadata": {
    "source_url": "https://www.gov.br/saude/pt-br/assuntos/noticias/2026/marco/ministerio-da-saude-e-ipea-debatem-indice-de-vulnerabilidade-social-e-ambiental-para-o-sus",
    "published_date": "2026-03-20 19:02:10-03:00",
    "agency": "saude",
    "theme_level_1": "Meio Ambiente e Sustentabilidade",
    "size_category": "Média"
  }
}