{
  "id": "doc_05_10",
  "title": "CBPF abre inscrições abertas para a I Escola Teórica de Campos e Partículas do Rio de Janeiro",
  "content": "O Centro Brasileiro de Pesquisas Físicas (CBPF) será palco da I Escola Teórica de Campos e Partículas do Rio de Janeiro (EsCamPa 2026-CBPF), que tem como objetivo principal contribuir para a formação de recursos humanos na área.\n\nDe 23 de fevereiro a 6 de março, cursos básicos e avançados, além de seminários, serão ministrados por professores e pesquisadores de diferentes instituições. Pensada para incentivar, aprofundar e ampliar a cultura geral dos participantes, a escola também tem a proposta de promover a integração e a união da comunidade de pesquisadores e estudantes da área.\n\nAs inscrições vão até o dia 14 de fevereiro e podem ser feitas no site do evento. Os estudantes que desejarem poderão, no ato da inscrição, submeter um título para apresentação de pôster, que ocorrerá nos dias 25 de fevereiro e 4 de março. Em cada semana, os organizadores julgarão os trabalhos apresentados, selecionando o melhor pôster, que receberá prêmio e certificado.\n\n**Serviço:**\n\n**I Escola Teórica de Campos e Partículas do Rio de Janeiro – EsCamPa 2026-CBPF**\n\n**Data**: de 23/02/2026 a 06/06/2026\n\n**Horário**: das 9h às 17h30\n\n**Local**: Auditório Ministro João Alberto Lins de Barros – Rua Dr. Xavier Sigaud, 150 – Urca – Rio de Janeiro.\n\n**Inscrições e informações sobre programação**:\n\n<https://sites.google.com/view/escampa-2026/>\n\n**E-mail de contato**: [escampa.rj@gmail.com](mailto:escampa.rj@gmail.com)",
  "category": "Ciência e Tecnologia",
  "length": 1413,
  "metadata": {
    "source_url": "https://www.gov.br/cbpf/pt-br/assuntos/noticias/cbpf-abre-inscricoes-abertas-para-a-i-escola-teorica-de-campos-e-particulas-do-rio-de-janeiro",
    "published_date": "2026-01-16 15:57:24-03:00",
    "agency": "cbpf",
    "theme_level_1": "Ciência, Tecnologia e Inovação",
    "size_category": "Curta"
  }
}