{
  "id": "doc_17_14",
  "title": "Alckmin e Padilha aplicam primeiras doses da vacina contra a dengue fabricada no Brasil",
  "content": "Medicamento foi desenvolvido pelo Butantan, que recebeu hoje mais R$ 1,4 bi para construção de novas fábricas de imunizantes\n![55086676736_ca73c3dd0f_k.jpg](https://www.gov.br/mdic/pt-br/assuntos/noticias/2026/fevereiro/alckmin-e-padilha-aplicam-primeiras-doses-da-vacina-contra-a-dengue-fabricada-no-brasil/55086676736_ca73c3dd0f_k.jpg/@@images/2cac9802-6780-48a7-81e2-84da374604cd.jpeg)\n\nO vice-presidente da República e ministro do Desenvolvimento, Indústria, Comércio e Serviços (MDIC), Geraldo Alckmin, e o ministro da Saúde, Alexandre Padilha, aplicaram nesta segunda-feira (9/2) a vacina contra a dengue fabricada no Brasil, durante evento ao lado do presidente Luiz Inácio Lula da Silva e outros ministros, no Instituto Butantan, em São Paulo.\n\n“Ajudar o Butantan é ter apenas a primazia de dizer que a gente está ajudando 215 milhões de almas que vivem neste país e que precisam”, garantiu o presidente Lua. \n\nA produção de medicamentos e dispositivos médicos no país está entre os objetivos e metas da Missão 2 da Nova Indústria Brasil (NIB), voltada para o fortalecimento com Complexo Econômico-Industrial da Saúde. A partir de hoje, todos os profissionais de saúde do país cadastrados nas Unidades Básicas de Saúde (UBS) já podem ser imunizados contra a dengue com a Butantan-DV, primeira vacina produzida integralmente no Brasil.\n\n“Vacina é política pública, é Estado presente. Ao investir no Instituto Butantan, o governo do presidente Lula reafirma que saúde, ciência e vida são prioridades nacionais”, afirmou Alckmin.\n\nNo mesmo evento, foram assinadas ordens de serviço para a construção de duas novas fábricas e a modernização de outras duas unidades. O investimento do governo federal é de R$ 1,4 bilhão, com recursos do Novo PAC Saúde, voltado à ampliação da infraestrutura e da capacidade produtiva de vacinas e insumos biológicos.\n\nAs obras têm como objetivo garantir autonomia nacional na fabricação de soros e imunizantes avançados, incluindo vacinas de RNA mensageiro (RNAm), além de Insumos Farmacêuticos Ativos (IFAs) das vacinas DTPa e HPV, ampliando a autonomia do Sistema Único de Saúde (SUS). A tecnologia de RNA mensageiro fornece instruções temporárias às células para ativar o sistema imunológico, sem o uso de vírus vivos e sem alterar o DNA humano.\n\nAs novas plantas permitirão capacidade anual de até 6 milhões de doses da vacina DTPa, com investimento de R$ 550,7 milhões; e de 20 milhões de doses da vacina contra o HPV, com aporte superior a R$ 495,9 milhões. A unidade de soros e área multipropósito, com investimentos de R$ 232,5 milhões, terá capacidade inicial de 1,2 milhão de frascos de soro concentrado por ano, podendo alcançar 5,5 milhões de frascos de soro líquido ao ano após a conclusão das obras.\n\n“O Instituto Butantan nasceu da necessidade de proteger a população. Hoje, com os investimentos do governo do presidente Lula, ele se projeta para o futuro como um dos pilares da produção nacional de vacinas e da segurança sanitária do país”, disse o vice-presidente.\n\n**Butantan**\n\nO instituto é o maior produtor de vacinas e soros da América Latina e o principal fabricante de imunobiológicos do Brasil. Referência internacional em eficiência e qualidade, é responsável pela maior parte dos soros hiperimunes utilizados no país e por 100% das vacinas contra o vírus influenza utilizadas na Campanha Nacional de Vacinação contra a Gripe.\n\nTambém atua em pesquisa básica e aplicada, com foco em agentes patogênicos, inovação e modernização de processos produtivos. Desenvolve ainda estudos clínicos, terapêuticos e epidemiológicos voltados à saúde pública.  \n\n**Mauá**\n\nÀ tarde, Alckmin participou ao lado do presidente Lula do anúncio de investimentos estruturantes em educação e saúde no município de Mauá, no ABC Paulista. As ações incluem R$ 44,8 milhões do Novo PAC para a aquisição e reforma do Campus Mauá do Instituto Federal de São Paulo (IFSP) e R$ 37,4 milhões para o Sistema Único de Saúde (SUS), com a implantação de policlínica, nova UBS, entrega de ambulâncias e reforço da atenção básica, sendo o maior investimento em infraestrutura social da história do município.\n\nEm sua fala, o vice-presidente saudou a estratégia integrada que articula educação, saúde, indústria e geração de empregos, nos marcos da Nova Indústria Brasil (NIB).\n\n“Hoje o presidente começou no Instituto Butantan. E aí é fortalecer a indústria da saúde. Vacinas, equipamentos, como aqui nós vimos, tomógrafos, ressonância, indústria da saúde, que é uma indústria que vai crescer muito”, afirmou\n\nAlckmin ressaltou ainda que a agenda anunciada em Mauá está diretamente conectada à política industrial do governo.\n\n“O presidente Lula está dando um forte impulso à indústria química, petroquímica, automotiva e de autopeças, com programas como o carro sustentável e a renovação da frota de caminhões. Desenvolvimento econômico e política social caminham juntos. O mais importante é a vida, mas ela anda junto com emprego, renda e uma indústria forte”, concluiu.\n\nPara mais informações sobre a agenda em Mauá, [clique aqui](https://www.gov.br/planalto/pt-br/acompanhe-o-planalto/noticias/2026/02/lula-anuncia-novo-instituto-federal-e-o-maior-investimento-em-saude-da-historia-de-maua-sp).",
  "category": "Saúde",
  "length": 5223,
  "metadata": {
    "source_url": "https://www.gov.br/mdic/pt-br/assuntos/noticias/2026/fevereiro/alckmin-e-padilha-aplicam-primeiras-doses-da-vacina-contra-a-dengue-fabricada-no-brasil",
    "published_date": "2026-02-09 14:02:00-03:00",
    "agency": "mdic",
    "theme_level_1": "Saúde",
    "size_category": "Média"
  }
}